yarrow/__init__.py
yarrow/_version.py
yarrow/_yarrow_version.py
yarrow/main.py
yarrow/utils.py
yarrow/yarrow.py
yarrow/yarrow_cls.py
yarrow/cli/__init__.py
yarrow/cli/check.py
yarrow/cli/open.py
yarrow/cli/save.py
pyyarrow-1.0.3.dist-info/LICENSE
pyyarrow-1.0.3.dist-info/METADATA
pyyarrow-1.0.3.dist-info/WHEEL
pyyarrow-1.0.3.dist-info/entry_points.txt
pyyarrow-1.0.3.dist-info/top_level.txt
pyyarrow-1.0.3.dist-info/RECORD
