Metadata-Version: 2.1
Name: pyyarrow
Version: 1.0.3
Summary: Yarrow Format parsing lib
Home-page: https://github.com/michelin/YarrowFormat
Author: Mathieu Pichon
Author-email: mathieu.pichon_ext@michelin.com
License: UNKNOWN
Platform: UNKNOWN
Requires-Python: >= 3.6
Requires-Dist: setuptools
Requires-Dist: wheel
Requires-Dist: click
Requires-Dist: numpy ; python_version >= "1.19"
Requires-Dist: pydantic ; python_version >= "1.8"
Provides-Extra: dev
Requires-Dist: black ; extra == 'dev'
Requires-Dist: isort ; extra == 'dev'
Requires-Dist: pytest ; extra == 'dev'
Requires-Dist: pytest-cov ; extra == 'dev'
Requires-Dist: sphinx ; extra == 'dev'
Requires-Dist: sphinx-rtd-theme ; extra == 'dev'
